rust_demangler/__init__.py
rust_demangler/main.py
rust_demangler/rust.py
rust_demangler/rust_legacy.py
rust_demangler/rust_v0.py
rust_demangler-1.0.dist-info/METADATA
rust_demangler-1.0.dist-info/WHEEL
rust_demangler-1.0.dist-info/top_level.txt
rust_demangler-1.0.dist-info/RECORD
