Metadata-Version: 2.1
Name: rust-demangler
Version: 1.0
Summary: A package for demangling Rust symbols
Home-page: https://github.com/teambi0s/rust_demangler
Author: bi0s
Author-email: amritabi0s1@example.com
License: UNKNOWN
Platform: UNKNOWN
Classifier: Programming Language :: Python :: 3
Classifier: License :: OSI Approved :: MIT License
Classifier: Operating System :: OS Independent
